pymodaq_plugins_uniblitz/__init__.py
pymodaq_plugins_uniblitz/utils.py
pymodaq_plugins_uniblitz/app/__init__.py
pymodaq_plugins_uniblitz/daq_move_plugins/__init__.py
pymodaq_plugins_uniblitz/daq_move_plugins/daq_move_VLM1.py
pymodaq_plugins_uniblitz/daq_viewer_plugins/__init__.py
pymodaq_plugins_uniblitz/daq_viewer_plugins/plugins_0D/__init__.py
pymodaq_plugins_uniblitz/daq_viewer_plugins/plugins_1D/__init__.py
pymodaq_plugins_uniblitz/daq_viewer_plugins/plugins_2D/__init__.py
pymodaq_plugins_uniblitz/daq_viewer_plugins/plugins_ND/__init__.py
pymodaq_plugins_uniblitz/exporters/__init__.py
pymodaq_plugins_uniblitz/extensions/__init__.py
pymodaq_plugins_uniblitz/hardware/__init__.py
pymodaq_plugins_uniblitz/models/__init__.py
pymodaq_plugins_uniblitz/resources/__init__.py
pymodaq_plugins_uniblitz/resources/config_template.toml
pymodaq_plugins_uniblitz/scanners/__init__.py
pymodaq_plugins_uniblitz-5.1.0.dist-info/METADATA
pymodaq_plugins_uniblitz-5.1.0.dist-info/WHEEL
pymodaq_plugins_uniblitz-5.1.0.dist-info/entry_points.txt
pymodaq_plugins_uniblitz-5.1.0.dist-info/licenses/LICENSE
pymodaq_plugins_uniblitz-5.1.0.dist-info/RECORD
