Metadata-Version: 2.4
Name: pymodaq_plugins_uniblitz
Version: 5.1.0
Summary: Plugin for Uniblitz Shutters
Project-URL: Homepage, https://pymodaq.cnrs.fr
Project-URL: Documentation , https://pymodaq.cnrs.fr
Project-URL: Repository , https://github.com/Attolab/pymodaq_plugins_uniblitz
Author-email: Matthieu Guer <matthieu.guer@cea.fr>, Romain Geneaux <romain.geneaux@cea.fr>
Maintainer-email: Romain Geneaux <romain.geneaux@cea.fr>
License: The MIT License (MIT)
License-File: LICENSE
Classifier: Development Status :: 5 - Production/Stable
Classifier: Intended Audience :: Science/Research
Classifier: License :: OSI Approved :: MIT License
Classifier: Natural Language :: English
Classifier: Operating System :: OS Independent
Classifier: Programming Language :: Python :: 3.8
Classifier: Programming Language :: Python :: 3.9
Classifier: Programming Language :: Python :: 3.10
Classifier: Programming Language :: Python :: 3.11
Classifier: Topic :: Scientific/Engineering :: Human Machine Interfaces
Classifier: Topic :: Scientific/Engineering :: Visualization
Classifier: Topic :: Software Development :: Libraries :: Python Modules
Classifier: Topic :: Software Development :: User Interfaces
Requires-Python: >=3.8
Requires-Dist: pymodaq>=5.0.0
Requires-Dist: pyserial
